pytrainer/__init__.py
pytrainer/config.py
pytrainer/engine.py
pytrainer/train.py
pytrainer/utils.py
pytrainer/data/your_dataset.txt
pyaitrainer-0.1.1.dist-info/METADATA
pyaitrainer-0.1.1.dist-info/WHEEL
pyaitrainer-0.1.1.dist-info/top_level.txt
pyaitrainer-0.1.1.dist-info/RECORD
