Metadata-Version: 2.4
Name: pyaitrainer
Version: 0.1.1
Summary: Minimal transformer-based character-level trainer
Home-page: https://github.com/timurko7674/PyTrainer
Author: I'm_caca
Author-email: I'm_caca <bababui544@gmail.com>
License: MIT
Requires-Python: >=3.7
Requires-Dist: torch
Dynamic: author
Dynamic: home-page
Dynamic: requires-python
